byted_overpass_data_edc_srv_product_build/__init__.py
byted_overpass_data_edc_srv_product_build-0.0.1.dist-info/METADATA
byted_overpass_data_edc_srv_product_build-0.0.1.dist-info/WHEEL
byted_overpass_data_edc_srv_product_build-0.0.1.dist-info/top_level.txt
byted_overpass_data_edc_srv_product_build-0.0.1.dist-info/RECORD
